Estudos/FPGA/Exemplos VHDL/Projetos VHDL 2ª Aula/Projeto flipflop jk/flipflop_jk.vhd
library ieee;
use ieee.std_logic_1164.all;

entity flipflop_jk is
  port (
    clk : in std_logic;
    J   : in std_logic;
    K   : in std_logic;
    Q   : out std_logic
  );
end entity;

architecture rtl of flipflop_jk is
  signal q_reg : std_logic := '0';
begin
  process(clk)
  begin
    if rising_edge(clk) then
      if J = '0' and K = '0' then
        q_reg <= q_reg;           -- mantém
      elsif J = '0' and K = '1' then
        q_reg <= '0';             -- reset
      elsif J = '1' and K = '0' then
        q_reg <= '1';             -- set
      elsif J = '1' and K = '1' then
        q_reg <= not q_reg;       -- toggle
      end if;
    end if;
  end process;
  Q <= q_reg;
end architecture;

Estudos/FPGA/Exemplos VHDL/Projetos VHDL 2ª Aula/Projeto flipflop jk/tb_flipflop_jk.vhd
library ieee;
use ieee.std_logic_1164.all;

entity tb_flipflop_jk is
end;

architecture sim of tb_flipflop_jk is
  signal clk : std_logic := '0';
  signal J, K, Q : std_logic;
begin
  DUT: entity work.flipflop_jk port map (clk => clk, J => J, K => K, Q => Q);

  clk_gen: process
  begin
    for i in 0 to 7 loop
      clk <= '0'; wait for 10 ns;
      clk <= '1'; wait for 10 ns;
    end loop;
    wait;
  end process;

  stim_proc: process
  begin
    J <= '0'; K <= '0'; wait for 20 ns;
    J <= '1'; K <= '0'; wait for 20 ns;
    J <= '0'; K <= '1'; wait for 20 ns;
    J <= '1'; K <= '1'; wait for 20 ns;
    wait;
  end process;
end architecture;

Estudos/FPGA/Exemplos VHDL/Projetos VHDL 2ª Aula/Projeto flipflop jk/flipflop_jk.vcd
$date
  Tue Sep  2 12:43:44 2025
$end
$version
  GHDL v0
$end
$timescale
  1 fs
$end
$scope module standard $end
$upscope $end
$scope module std_logic_1164 $end
$upscope $end
$scope module tb_flipflop_jk $end
$var reg 1 ! clk $end
$var reg 1 " j $end
$var reg 1 # k $end
$var reg 1 $ q $end
$scope module dut $end
$var reg 1 % clk $end
$var reg 1 & j $end
$var reg 1 ' k $end
$var reg 1 ( q $end
$var reg 1 ) q_reg $end
$upscope $end
$upscope $end
$enddefinitions $end
#0
0!
0"
0#
0$
0%
0&
0'
0(
0)
#10000000
1!
1%
#20000000
0!
1"
0%
1&
#30000000
1!
1$
1%
1(
1)
#40000000
0!
0"
1#
0%
0&
1'
#50000000
1!
0$
1%
0(
0)
#60000000
0!
1"
0%
1&
#70000000
1!
1$
1%
1(
1)
#80000000
0!
0%
#90000000
1!
0$
1%
0(
0)
#100000000
0!
0%
#110000000
1!
1$
1%
1(
1)
#120000000
0!
0%
#130000000
1!
0$
1%
0(
0)
#140000000
0!
0%
#150000000
1!
1$
1%
1(
1)
