Estudos/FPGA/Mentorias/Exercício 12.09.25/DetectorVetorialdeMealy.vhd
-- RESIDÊNCIA PROFISSIONAL EM FPGA
-- EmbarcaTech IFMA MTC
-- Discente: Renato da Fonseca Oliveira

-- ATIVIDADE
-- Faça um exemplo que detecte a ordem de vetores 001, 100, 101, 011 em Mealy

library ieee;
use ieee.std_logic_1164.all;

entity DetectorVetorialdeMealy is
    port (
        clk       : in std_logic;
        reset     : in std_logic;
        digit     : in std_logic_vector(2 downto 0); -- vetor de 3 bits (0-7)
        detected  : out std_logic                    -- sequência detectada
    );
end DetectorVetorialdeMealy;

architecture mealy of DetectorVetorialdeMealy is
    type state_type is (S0, S1, S2, S3);
    signal state, next_state : state_type;
begin
    
    -- Registrador de estado (síncrono)
    process(clk, reset)
    begin
        if reset = '1' then
            state <= S0;
        elsif rising_edge(clk) then
            state <= next_state;
        end if;
    end process;

    
    -- Lógica de transição de estados e saída (Mealy)
    process(state, digit)
    begin
        -- Valores padrão
        next_state <= S0;
        detected <= '0';
        
        case state is
            when S0 =>
                if digit = "001" then 
                    next_state <= S1;
                else
                    next_state <= S0;
                end if;

            when S1 =>
                if digit = "100" then 
                    next_state <= S2;
                elsif digit = "001" then
                    next_state <= S1; -- possível reinício imediato
                else
                    next_state <= S0;
                end if;

            when S2 =>
                if digit = "101" then
                    next_state <= S3;
                elsif digit = "001" then
                    next_state <= S1;
                else
                    next_state <= S0;
                end if;

            when S3 =>
                if digit = "011" then
                    detected <= '1'; -- Mealy: saída depende do estado atual e da entrada
                    next_state <= S0;
                elsif digit = "001" then
                    next_state <= S1;
                else
                    next_state <= S0;
                end if;

            when others =>
                next_state <= S0;
                detected <= '0';
        end case;
    end process;

end architecture mealy;

Estudos/FPGA/Mentorias/Exercício 12.09.25/tbDetectorVetorialdeMealy.vhd
-- RESIDÊNCIA PROFISSIONAL EM FPGA
-- EmbarcaTech IFMA MTC
-- Discente: Renato da Fonseca Oliveira

-- ATIVIDADE
-- Faça um exemplo que detecte a ordem de vetores 001, 100, 101, 011 em Mealey

library ieee;
use ieee.std_logic_1164.all;

entity tbDetectorVetorialdeMealy  is
end tbDetectorVetorialdeMealy ;

architecture sim of tbDetectorVetorialdeMealy  is
    signal clk       : std_logic := '0';
    signal reset     : std_logic := '1';
    signal digit     : std_logic_vector(2 downto 0) := "000";
    signal detected  : std_logic;

    component DetectorVetorialdeMealy 
        port (
            clk       : in std_logic;
            reset     : in std_logic;
            digit     : in std_logic_vector(2 downto 0);
            detected  : out std_logic
        );
    end component;
begin
    uut: DetectorVetorialdeMealy
        port map (
            clk       => clk,
            reset     => reset,
            digit     => digit,
            detected  => detected
        );

    -- Clock de 20 ns
    clk_process: process
    begin
        while true loop
            clk <= '0'; wait for 10 ns;
            clk <= '1'; wait for 10 ns;
        end loop;
    end process;

    -- Estímulos alinhados a borda de clock (cada wait for 20 ns = um período)
    stim_proc: process
    begin
        -- Reset inicial
        reset <= '1'; wait for 25 ns;
        reset <= '0'; wait for 15 ns; -- alinhado para cair antes do próximo posedge

        -- Teste 1: Sequência CORRETA: 001 -> 100 -> 101 -> 011 (deve detectar)
        report "Teste 1: Sequencia CORRETA: 001 -> 100 -> 101 -> 011";
        digit <= "001"; wait for 20 ns;
        digit <= "100"; wait for 20 ns;
        digit <= "101"; wait for 20 ns;
        digit <= "011"; wait for 20 ns; -- aqui detected deve ser '1'
        wait for 20 ns;

        -- Teste 2: Sequência com erro no meio: 001 -> 100 -> 000 -> 011 (não detecta)
        report "Teste 2: Sequencia com erro: 001 -> 100 -> 000 -> 011";
        digit <= "001"; wait for 20 ns;
        digit <= "100"; wait for 20 ns;
        digit <= "000"; wait for 20 ns;
        digit <= "011"; wait for 20 ns; -- não deve detectar
        wait for 20 ns;

        -- Teste 3: Reinício imediato se aparecer 001 no meio
        report "Teste 3: Reinicio imediato: 001 -> 100 -> 001 -> 100 -> 101 -> 011";
        digit <= "001"; wait for 20 ns; -- S1
        digit <= "100"; wait for 20 ns; -- S2
        digit <= "001"; wait for 20 ns; -- detecta reinício -> S1
        digit <= "100"; wait for 20 ns; -- S2
        digit <= "101"; wait for 20 ns; -- S3
        digit <= "011"; wait for 20 ns; -- detecta ('1')
        wait for 20 ns;

        -- Teste 4: Duas detecções consecutivas (sequências seguidas)
        report "Teste 4: Duas detecoes consecutivas";
        digit <= "001"; wait for 20 ns;
        digit <= "100"; wait for 20 ns;
        digit <= "101"; wait for 20 ns;
        digit <= "011"; wait for 20 ns; -- detect 1
        digit <= "001"; wait for 20 ns; -- inicia nova possível sequência
        digit <= "100"; wait for 20 ns;
        digit <= "101"; wait for 20 ns;
        digit <= "011"; wait for 20 ns; -- detect 1 novamente
        wait for 40 ns;

        report "Fim dos testes";
        wait;
    end process;
end sim;

Estudos/FPGA/Mentorias/Exercício 12.09.25/DetectorVetorialdeMealy.vcd
$date
  Fri Sep 12 18:51:57 2025
$end
$version
  GHDL v0
$end
$timescale
  1 fs
$end
$scope module standard $end
$upscope $end
$scope module std_logic_1164 $end
$upscope $end
$scope module tbdetectorvetorialdemealy $end
$var reg 1 ! clk $end
$var reg 1 " reset $end
$var reg 3 # digit[2:0] $end
$var reg 1 $ detected $end
$scope module uut $end
$var reg 1 % clk $end
$var reg 1 & reset $end
$var reg 3 ' digit[2:0] $end
$var reg 1 ( detected $end
$comment state is not handled $end
$comment next_state is not handled $end
$upscope $end
$upscope $end
$enddefinitions $end
#0
0!
1"
b000 #
0$
0%
1&
b000 '
0(
#10000000
1!
1%
#20000000
0!
0%
#25000000
0"
0&
#30000000
1!
1%
#40000000
0!
b001 #
0%
b001 '
#50000000
1!
1%
#60000000
0!
b100 #
0%
b100 '
#70000000
1!
1%
#80000000
0!
b101 #
0%
b101 '
#90000000
1!
1%
#100000000
0!
b011 #
1$
0%
b011 '
1(
#110000000
1!
0$
1%
0(
#120000000
0!
0%
#130000000
1!
1%
#140000000
0!
b001 #
0%
b001 '
#150000000
1!
1%
#160000000
0!
b100 #
0%
b100 '
#170000000
1!
1%
#180000000
0!
b000 #
0%
b000 '
#190000000
1!
1%
#200000000
0!
b011 #
0%
b011 '
#210000000
1!
1%
#220000000
0!
0%
#230000000
1!
1%
#240000000
0!
b001 #
0%
b001 '
#250000000
1!
1%
#260000000
0!
b100 #
0%
b100 '
#270000000
1!
1%
#280000000
0!
b001 #
0%
b001 '
#290000000
1!
1%
#300000000
0!
b100 #
0%
b100 '
#310000000
1!
1%
#320000000
0!
b101 #
0%
b101 '
#330000000
1!
1%
#340000000
0!
b011 #
1$
0%
b011 '
1(
#350000000
1!
0$
1%
0(
#360000000
0!
0%
#370000000
1!
1%
#380000000
0!
b001 #
0%
b001 '
#390000000
1!
1%
#400000000
0!
b100 #
0%
b100 '
#410000000
1!
1%
#420000000
0!
b101 #
0%
b101 '
#430000000
1!
1%
#440000000
0!
b011 #
1$
0%
b011 '
1(
#450000000
1!
0$
1%
0(
#460000000
0!
b001 #
0%
b001 '
#470000000
1!
1%
#480000000
0!
b100 #
0%
b100 '
#490000000
1!
1%
#500000000
0!
b101 #
0%
b101 '
#510000000
1!
1%
#520000000
0!
b011 #
1$
0%
b011 '
1(
#530000000
1!
0$
1%
0(
