Estudos/FPGA/Tarefas/TarefaU5C1/d_flip_flop.vhd
library IEEE;
use IEEE.STD_LOGIC_1164.ALL;

entity d_flip_flop is
    Port (
        D   : in  STD_LOGIC;
        CLK : in  STD_LOGIC;
        Q   : out STD_LOGIC;
        Qn  : out STD_LOGIC
    );
end d_flip_flop;

architecture Behavioral of d_flip_flop is
    signal Q_int : STD_LOGIC := '0';
begin
    process(CLK)
    begin
        if rising_edge(CLK) then
            Q_int <= D;
        end if;
    end process;

    Q  <= Q_int;
    Qn <= not Q_int;
end Behavioral;

Estudos/FPGA/Tarefas/TarefaU5C1/reg8.vhd
library IEEE;
use IEEE.STD_LOGIC_1164.ALL;

entity reg8 is
    Port (
        D_in : in  STD_LOGIC_VECTOR(7 downto 0);
        CLK  : in  STD_LOGIC;
        Q_out: out STD_LOGIC_VECTOR(7 downto 0);
        Qn_out: out STD_LOGIC_VECTOR(7 downto 0)
    );
end reg8;

architecture Structural of reg8 is
    component d_flip_flop
        Port (
            D   : in  STD_LOGIC;
            CLK : in  STD_LOGIC;
            Q   : out STD_LOGIC;
            Qn  : out STD_LOGIC
        );
    end component;

begin
    gen_ff: for i in 0 to 7 generate
        ff_inst: d_flip_flop
            port map (
                D   => D_in(i),
                CLK => CLK,
                Q   => Q_out(i),
                Qn  => Qn_out(i)
            );
    end generate;
end Structural;

Estudos/FPGA/Tarefas/TarefaU5C1/tb_reg8.vhd
library IEEE;
use IEEE.STD_LOGIC_1164.ALL;

entity tb_reg8 is
end tb_reg8;

architecture sim of tb_reg8 is
    signal D_in   : STD_LOGIC_VECTOR(7 downto 0) := (others => '0');
    signal CLK    : STD_LOGIC := '0';
    signal Q_out  : STD_LOGIC_VECTOR(7 downto 0);
    signal Qn_out : STD_LOGIC_VECTOR(7 downto 0);

    component reg8
        Port (
            D_in : in  STD_LOGIC_VECTOR(7 downto 0);
            CLK  : in  STD_LOGIC;
            Q_out: out STD_LOGIC_VECTOR(7 downto 0);
            Qn_out: out STD_LOGIC_VECTOR(7 downto 0)
        );
    end component;
begin
    uut: reg8
        port map (
            D_in   => D_in,
            CLK    => CLK,
            Q_out  => Q_out,
            Qn_out => Qn_out
        );

    -- Geração do clock
    clk_process: process
    begin
        CLK <= '0';
        wait for 10 ns;
        CLK <= '1';
        wait for 10 ns;
    end process;

    -- Estímulos
    stim_proc: process
    begin
        wait for 5 ns;
        D_in <= "10101010";
        wait for 20 ns;
        D_in <= "11110000";
        wait for 20 ns;
        D_in <= "00001111";
        wait for 20 ns;
        D_in <= "11001100";
        wait for 20 ns;
        wait;
    end process;
end sim;

Estudos/FPGA/Tarefas/TarefaU5C1/ondas.vcd
$date
  Mon Oct  6 00:21:37 2025
$end
$version
  GHDL v0
$end
$timescale
  1 fs
$end
$scope module standard $end
$upscope $end
$scope module std_logic_1164 $end
$upscope $end
$scope module tb_reg8 $end
$var reg 8 ! d_in[7:0] $end
$var reg 1 " clk $end
$var reg 8 # q_out[7:0] $end
$var reg 8 $ qn_out[7:0] $end
$scope module uut $end
$var reg 8 % d_in[7:0] $end
$var reg 1 & clk $end
$var reg 8 ' q_out[7:0] $end
$var reg 8 ( qn_out[7:0] $end
$scope module gen_ff(0) $end
$scope module ff_inst $end
$var reg 1 ) d $end
$var reg 1 * clk $end
$var reg 1 + q $end
$var reg 1 , qn $end
$var reg 1 - q_int $end
$upscope $end
$upscope $end
$scope module gen_ff(1) $end
$scope module ff_inst $end
$var reg 1 . d $end
$var reg 1 / clk $end
$var reg 1 0 q $end
$var reg 1 1 qn $end
$var reg 1 2 q_int $end
$upscope $end
$upscope $end
$scope module gen_ff(2) $end
$scope module ff_inst $end
$var reg 1 3 d $end
$var reg 1 4 clk $end
$var reg 1 5 q $end
$var reg 1 6 qn $end
$var reg 1 7 q_int $end
$upscope $end
$upscope $end
$scope module gen_ff(3) $end
$scope module ff_inst $end
$var reg 1 8 d $end
$var reg 1 9 clk $end
$var reg 1 : q $end
$var reg 1 ; qn $end
$var reg 1 < q_int $end
$upscope $end
$upscope $end
$scope module gen_ff(4) $end
$scope module ff_inst $end
$var reg 1 = d $end
$var reg 1 > clk $end
$var reg 1 ? q $end
$var reg 1 @ qn $end
$var reg 1 A q_int $end
$upscope $end
$upscope $end
$scope module gen_ff(5) $end
$scope module ff_inst $end
$var reg 1 B d $end
$var reg 1 C clk $end
$var reg 1 D q $end
$var reg 1 E qn $end
$var reg 1 F q_int $end
$upscope $end
$upscope $end
$scope module gen_ff(6) $end
$scope module ff_inst $end
$var reg 1 G d $end
$var reg 1 H clk $end
$var reg 1 I q $end
$var reg 1 J qn $end
$var reg 1 K q_int $end
$upscope $end
$upscope $end
$scope module gen_ff(7) $end
$scope module ff_inst $end
$var reg 1 L d $end
$var reg 1 M clk $end
$var reg 1 N q $end
$var reg 1 O qn $end
$var reg 1 P q_int $end
$upscope $end
$upscope $end
$upscope $end
$upscope $end
$enddefinitions $end
#0
b00000000 !
0"
b00000000 #
b11111111 $
b00000000 %
0&
b00000000 '
b11111111 (
0)
0*
0+
1,
0-
0.
0/
00
11
02
03
04
05
16
07
08
09
0:
1;
0<
0=
0>
0?
1@
0A
0B
0C
0D
1E
0F
0G
0H
0I
1J
0K
0L
0M
0N
1O
0P
#5000000
b10101010 !
b10101010 %
1.
18
1B
1L
#10000000
1"
b10101010 #
b01010101 $
1&
b10101010 '
b01010101 (
1*
1/
10
01
12
14
19
1:
0;
1<
1>
1C
1D
0E
1F
1H
1M
1N
0O
1P
#20000000
0"
0&
0*
0/
04
09
0>
0C
0H
0M
#25000000
b11110000 !
b11110000 %
0.
08
1=
1G
#30000000
1"
b11110000 #
b00001111 $
1&
b11110000 '
b00001111 (
1*
1/
00
11
02
14
19
0:
1;
0<
1>
1?
0@
1A
1C
1H
1I
0J
1K
1M
#40000000
0"
0&
0*
0/
04
09
0>
0C
0H
0M
#45000000
b00001111 !
b00001111 %
1)
1.
13
18
0=
0B
0G
0L
#50000000
1"
b00001111 #
b11110000 $
1&
b00001111 '
b11110000 (
1*
1+
0,
1-
1/
10
01
12
14
15
06
17
19
1:
0;
1<
1>
0?
1@
0A
1C
0D
1E
0F
1H
0I
1J
0K
1M
0N
1O
0P
#60000000
0"
0&
0*
0/
04
09
0>
0C
0H
0M
#65000000
b11001100 !
b11001100 %
0)
0.
1G
1L
#70000000
1"
b11001100 #
b00110011 $
1&
b11001100 '
b00110011 (
1*
0+
1,
0-
1/
00
11
02
14
19
1>
1C
1H
1I
0J
1K
1M
1N
0O
1P
