Estudos/FPGA/Exemplos VHDL/Projetos VHDL 4ª Aula/7seg/bcd_7segmentos.vhd
-- Decodificador BCD para display de 7 segmentos (cátodo comum)
library IEEE;
use IEEE.std_logic_1164.all;
use IEEE.numeric_std.all;

entity bcd_7segmentos is
    port (
        bcd    : in std_logic_vector(3 downto 0);    -- Entrada BCD
        seg    : out std_logic_vector(6 downto 0)    -- Saída: segmentos a–g
    );
end bcd_7segmentos;

architecture behavioral of bcd_7segmentos is
begin
    process(bcd)
    begin
        case bcd is
        when "0000" => seg <= "1001000"; -- ASCII 'H' = 72
        when "0001" => seg <= "1001001"; -- ASCII 'I' = 73
        when "0010" => seg <= "1010010"; -- ASCII 'R' = 82
        when "0011" => seg <= "1001001"; -- ASCII 'I' = 73
        when "0100" => seg <= "1010011"; -- ASCII 'S' = 83
        when "0101" => seg <= "1001100"; -- ASCII 'L' = 76
        when "0110" => seg <= "1000001"; -- ASCII 'A' = 65
        when "0111" => seg <= "1011001"; -- ASCII 'Y' = 89
        when "1000" => seg <= "1001110"; -- ASCII 'N' = 78
        when "1001" => seg <= "1000101"; -- ASCII 'E' = 69
        when others => seg <= "0000000"; -- nada aceso
        end case;
    end process;
end behavioral;

Estudos/FPGA/Exemplos VHDL/Projetos VHDL 4ª Aula/7seg/tb_bcd_7segmentos.vhd
-- Testbench para decodificador BCD para 7 segmentos
library IEEE;
use IEEE.std_logic_1164.all;
use IEEE.numeric_std.all;

entity tb_bcd_7segmentos is
end tb_bcd_7segmentos;

architecture test of tb_bcd_7segmentos is
    signal bcd_tb : std_logic_vector(3 downto 0);
    signal seg_tb : std_logic_vector(6 downto 0);

    component bcd_7segmentos
        port (
            bcd : in std_logic_vector(3 downto 0);
            seg : out std_logic_vector(6 downto 0)
        );
    end component;
begin
    uut: bcd_7segmentos port map (
        bcd => bcd_tb,
        seg => seg_tb
    );

    stim_proc: process
    begin
        for i in 0 to 15 loop
            bcd_tb <= std_logic_vector(to_unsigned(i, 4));
            wait for 10 ns;
        end loop;
        wait;
    end process;
end test;

Estudos/FPGA/Exemplos VHDL/Projetos VHDL 4ª Aula/7seg/bcd_display.vcd
$date
  Wed Sep  3 14:39:15 2025
$end
$version
  GHDL v0
$end
$timescale
  1 fs
$end
$scope module standard $end
$upscope $end
$scope module std_logic_1164 $end
$upscope $end
$scope module numeric_std $end
$upscope $end
$scope module tb_bcd_7segmentos $end
$var reg 4 ! bcd_tb[3:0] $end
$var reg 7 " seg_tb[6:0] $end
$scope module uut $end
$var reg 4 # bcd[3:0] $end
$var reg 7 $ seg[6:0] $end
$upscope $end
$upscope $end
$enddefinitions $end
#0
b0000 !
b1001000 "
b0000 #
b1001000 $
#10000000
b0001 !
b1001001 "
b0001 #
b1001001 $
#20000000
b0010 !
b1010010 "
b0010 #
b1010010 $
#30000000
b0011 !
b1001001 "
b0011 #
b1001001 $
#40000000
b0100 !
b1010011 "
b0100 #
b1010011 $
#50000000
b0101 !
b1001100 "
b0101 #
b1001100 $
#60000000
b0110 !
b1000001 "
b0110 #
b1000001 $
#70000000
b0111 !
b1011001 "
b0111 #
b1011001 $
#80000000
b1000 !
b1001110 "
b1000 #
b1001110 $
#90000000
b1001 !
b1000101 "
b1001 #
b1000101 $
#100000000
b1010 !
b0000000 "
b1010 #
b0000000 $
#110000000
b1011 !
b1011 #
#120000000
b1100 !
b1100 #
#130000000
b1101 !
b1101 #
#140000000
b1110 !
b1110 #
#150000000
b1111 !
b1111 #
