Estudos/FPGA/ExerciciosPraticos/sistemadealarme/alarme.v
// ========================================
// Módulo: alarme
// Descrição: Ativa o alarme de segurança com base nos sensores
// ========================================
module alarme (
    input wire A,   // Janela
    input wire B,   // Porta
    input wire C,   // Sistema de segurança
    output wire Y   // Alarme
);

    // Expressão lógica: Y = A + (B & C)
    assign Y = A | (B & C);

endmodule

Estudos/FPGA/ExerciciosPraticos/sistemadealarme/alarme_tb.v
// ========================================
// Testbench: alarme_tb
// Descrição: Testa todas as combinações de entrada do módulo alarme
// Gera arquivo .vcd para visualização no GTKWave
// ========================================

`include "alarme.v"
`timescale 1ns / 1ps

module alarme_tb;

    // Entradas como registradores
    reg A, B, C;

    // Saída como fio
    wire Y;

    // Instancia o módulo sob teste (UUT)
    alarme uut (
        .A(A),
        .B(B),
        .C(C),
        .Y(Y)
    );

    initial begin
        // Geração do arquivo VCD para GTKWave
        $dumpfile("alarme.vcd");
        $dumpvars(0, alarme_tb);

        $display("A B C | Y");
        $display("-------------");

        // Testa as 8 combinações possíveis
        A=0; B=0; C=0; #10; $display("%b %b %b | %b", A, B, C, Y);
        A=0; B=0; C=1; #10; $display("%b %b %b | %b", A, B, C, Y);
        A=0; B=1; C=0; #10; $display("%b %b %b | %b", A, B, C, Y);
        A=0; B=1; C=1; #10; $display("%b %b %b | %b", A, B, C, Y);
        A=1; B=0; C=0; #10; $display("%b %b %b | %b", A, B, C, Y);
        A=1; B=0; C=1; #10; $display("%b %b %b | %b", A, B, C, Y);
        A=1; B=1; C=0; #10; $display("%b %b %b | %b", A, B, C, Y);
        A=1; B=1; C=1; #10; $display("%b %b %b | %b", A, B, C, Y);

        $finish;
    end

endmodule

Estudos/FPGA/ExerciciosPraticos/sistemadealarme/alarme.vcd
$date
	Thu Aug 21 14:22:01 2025
$end
$version
	Icarus Verilog
$end
$timescale
	1ps
$end
$scope module alarme_tb $end
$var wire 1 ! Y $end
$var reg 1 " A $end
$var reg 1 # B $end
$var reg 1 $ C $end
$scope module uut $end
$var wire 1 " A $end
$var wire 1 # B $end
$var wire 1 $ C $end
$var wire 1 ! Y $end
$upscope $end
$upscope $end
$enddefinitions $end
$comment Show the parameter values. $end
$dumpall
$end
#0
$dumpvars
0$
0#
0"
0!
$end
#10000
1$
#20000
0$
1#
#30000
1!
1$
#40000
0$
0#
1"
#50000
1$
#60000
0$
1#
#70000
1$
